<Rpt id="65d5d0c9ea7a40149b310f1295bbb9ae" name="页眉页脚" cols="90,130,120,100,100,70,85,80">
  <Params />
  <Data />
  <Setting papername="PrinterCustom" height="400" width="550" />
  <Header height="40">
    <Text colspan="2" val=":Global(报表名称) " fontsize="20" bold="1" underline="1" lbs="None" tbs="None" rbs="None" bbs="None" />
    <Text col="3" val=":Global(页号)&#xD;+ &quot;/&quot;&#xD;+ Global(总页数) " lbs="None" tbs="None" rbs="None" bbs="None" />
  </Header>
  <Body rows="25,25,25">
    <Matrix rowspan="3" colspan="2" tbl="个人成绩" repeatrowheader="1" repeatcolheader="1" rowsort="name" colsort="year,subject">
      <Corner>
        <Text rowspan="2" val="姓名\成绩" background="#FFD8D8D8" />
      </Corner>
      <RowHeader>
        <Level field="xm">
          <Text row="2" val=":Val(个人成绩,xm) " background="#FFD8D8D8" />
        </Level>
      </RowHeader>
      <ColHeader>
        <Level field="year">
          <Text col="1" val=":Val(个人成绩,year) " hideleftdup="1" background="#FFD8D8D8" />
        </Level>
        <Level field="subject">
          <Text row="1" col="1" val=":Val(个人成绩,subject) " background="#FFD8D8D8" />
        </Level>
      </ColHeader>
      <MRow>
        <Text row="2" col="1" val=":Val(个人成绩,score) " />
      </MRow>
    </Matrix>
  </Body>
  <Footer height="40">
    <Text colspan="2" val=":Global(日期时间)" lbs="None" tbs="None" rbs="None" bbs="None" />
    <Text col="3" val=":&quot;【&quot;&#xD;+ Global(水平页号) &#xD;+ &quot;-&quot;&#xD;+ Global(垂直页号) &#xD;+&quot;】&quot;" lbs="None" tbs="None" rbs="None" bbs="None" />
  </Footer>
</Rpt>